odoo/addons/auth_oidc/README.rst
odoo/addons/auth_oidc/__init__.py
odoo/addons/auth_oidc/__manifest__.py
odoo/addons/auth_oidc/controllers/__init__.py
odoo/addons/auth_oidc/controllers/main.py
odoo/addons/auth_oidc/data/auth_oauth_data.xml
odoo/addons/auth_oidc/demo/local_keycloak.xml
odoo/addons/auth_oidc/i18n/auth_oidc.pot
odoo/addons/auth_oidc/i18n/es.po
odoo/addons/auth_oidc/i18n/it.po
odoo/addons/auth_oidc/i18n/zh_CN.po
odoo/addons/auth_oidc/models/__init__.py
odoo/addons/auth_oidc/models/auth_oauth_provider.py
odoo/addons/auth_oidc/models/res_users.py
odoo/addons/auth_oidc/readme/CONFIGURE.md
odoo/addons/auth_oidc/readme/CONTRIBUTORS.md
odoo/addons/auth_oidc/readme/DESCRIPTION.md
odoo/addons/auth_oidc/readme/HISTORY.md
odoo/addons/auth_oidc/readme/INSTALL.md
odoo/addons/auth_oidc/readme/ROADMAP.md
odoo/addons/auth_oidc/readme/USAGE.md
odoo/addons/auth_oidc/static/description/icon.png
odoo/addons/auth_oidc/static/description/index.html
odoo/addons/auth_oidc/static/description/oauth-microsoft_azure-api_permissions.png
odoo/addons/auth_oidc/static/description/oauth-microsoft_azure-optional_claims.png
odoo/addons/auth_oidc/static/description/odoo-azure_ad_multitenant.png
odoo/addons/auth_oidc/tests/__init__.py
odoo/addons/auth_oidc/tests/test_auth_oidc_auth_code.py
odoo/addons/auth_oidc/tests/keycloak/keycloak-config.json
odoo/addons/auth_oidc/tests/keycloak/keycloak.sh
odoo/addons/auth_oidc/views/auth_oauth_provider.xml
odoo_addon_auth_oidc-18.0.1.1.0.2.dist-info/METADATA
odoo_addon_auth_oidc-18.0.1.1.0.2.dist-info/WHEEL
odoo_addon_auth_oidc-18.0.1.1.0.2.dist-info/top_level.txt
odoo_addon_auth_oidc-18.0.1.1.0.2.dist-info/RECORD
