Metadata-Version: 2.1
Name: odoo-addon-auth_oidc
Version: 18.0.1.1.0.2
Requires-Python: >=3.10
Requires-Dist: odoo==18.0.*
Requires-Dist: python-jose
Summary: Allow users to login through OpenID Connect Provider
Home-page: https://github.com/OCA/server-auth
License: AGPL-3
Author: =?utf-8?q?ICTSTUDIO=2C_Andr=C3=A9_Schenkels=2C_ACSONE_SA/NV=2C_Odoo_Community_Association_=28OCA=29?=
Author-email: support@odoo-community.org
Classifier: Programming Language :: Python
Classifier: Framework :: Odoo
Classifier: Framework :: Odoo :: 18.0
Classifier: License :: OSI Approved :: GNU Affero General Public License v3
